nobitex/__init__.py
nobitex_python-0.0.0.dev0.dist-info/METADATA
nobitex_python-0.0.0.dev0.dist-info/WHEEL
nobitex_python-0.0.0.dev0.dist-info/licenses/LICENSE
nobitex_python-0.0.0.dev0.dist-info/RECORD
