Metadata-Version: 2.4
Name: nobitex-python
Version: 0.0.0.dev0
Summary: Python SDK For Nobitex Exchange
Project-URL: Homepage, https://github.com/msinamsina/nobitex-python
Project-URL: Repository, https://github.com/msinamsina/nobitex-python.git
Project-URL: Issues, https://github.com/msinamsina/nobitex-python/issues
Author-email: Mohammad Sina Allahkaram <msinamsina@gmail.com>
License:                     GNU GENERAL PUBLIC LICENSE
License-File: LICENSE
Keywords: api,exchange,nobitex,request
Classifier: Development Status :: 3 - Alpha
Classifier: Intended Audience :: Developers
Classifier: License :: OSI Approved :: GNU General Public License v3 (GPLv3)
Classifier: Operating System :: OS Independent
Classifier: Programming Language :: Python :: 3
Classifier: Programming Language :: Python :: 3.9
Classifier: Programming Language :: Python :: 3.10
Classifier: Programming Language :: Python :: 3.11
Classifier: Programming Language :: Python :: 3.12
Classifier: Topic :: Scientific/Engineering :: Artificial Intelligence
Classifier: Topic :: Software Development :: Libraries :: Application Frameworks
Requires-Python: >=3.9
